CL_Chess/__init__.py
CL_Chess/askUserToGiveInput.py
CL_Chess/gameEngine.py
CL_Chess/generateBoard.py
CL_Chess/isValidMove.py
CL_Chess/main.py
CL_Chess/makeCoinFtoT.py
CL_Chess/moveDiagram.py
CL_Chess/printBoard.py
CL_Chess/printGameOver.py
CL_Chess/printWinPlayer.py
CL_Chess/stepsCountDiagram.py
CL_Chess_Nishnath-1.3.2.dist-info/METADATA
CL_Chess_Nishnath-1.3.2.dist-info/WHEEL
CL_Chess_Nishnath-1.3.2.dist-info/top_level.txt
CL_Chess_Nishnath-1.3.2.dist-info/RECORD
