Metadata-Version: 2.2
Name: CL_Chess_Nishnath
Version: 1.3.2
Summary: Play Chess
Home-page: https://github.com/NishnathRai/CL-Chess
Author: Nishnath Rai
Author-email: nishnathnishu1122@gmail.com
Classifier: Programming Language :: Python :: 3
Dynamic: author
Dynamic: author-email
Dynamic: classifier
Dynamic: description
Dynamic: description-content-type
Dynamic: home-page
Dynamic: summary
